webamon/__init__.py
webamon/py.typed
webamon-1.0.2.dist-info/licenses/LICENSE
webamon-1.0.2.dist-info/METADATA
webamon-1.0.2.dist-info/WHEEL
webamon-1.0.2.dist-info/top_level.txt
webamon-1.0.2.dist-info/RECORD
