Metadata-Version: 2.4
Name: webamon
Version: 1.0.2
Summary: Webamon SDK - Please use webamon-cli for threat intelligence and web search
Author: Webamon Team
License: MIT
Project-URL: Homepage, https://webamon.com
Project-URL: Documentation, https://webamon.com/api
Project-URL: Repository, https://github.com/webamon-org/webamon-cli
Project-URL: Bug Tracker, https://github.com/webamon-org/webamon-cli/issues
Project-URL: CLI Tool, https://pypi.org/project/webamon-cli/
Project-URL: Twitter, https://x.com/webamon_search
Project-URL: LinkedIn, https://www.linkedin.com/company/web-a-mon
Project-URL: Reddit, https://www.reddit.com/r/WebamonSearch/
Project-URL: YouTube, https://www.youtube.com/@Webamon
Keywords: webamon,threat-intelligence,security,search,cli,sdk
Classifier: Development Status :: 5 - Production/Stable
Classifier: Intended Audience :: Developers
Classifier: License :: OSI Approved :: MIT License
Classifier: Operating System :: OS Independent
Classifier: Programming Language :: Python :: 3
Classifier: Programming Language :: Python :: 3.7
Classifier: Programming Language :: Python :: 3.8
Classifier: Programming Language :: Python :: 3.9
Classifier: Programming Language :: Python :: 3.10
Classifier: Programming Language :: Python :: 3.11
Classifier: Programming Language :: Python :: 3.12
Classifier: Topic :: Software Development :: Libraries :: Python Modules
Classifier: Topic :: Security
Classifier: Topic :: Internet :: WWW/HTTP :: Indexing/Search
Requires-Python: >=3.7
License-File: LICENSE
Provides-Extra: dev
Requires-Dist: pytest; extra == "dev"
Requires-Dist: black; extra == "dev"
Requires-Dist: isort; extra == "dev"
Requires-Dist: mypy; extra == "dev"
Dynamic: license-file
